repo_smith/__init__.py
repo_smith/clone_from.py
repo_smith/command_result.py
repo_smith/initialize_repo.py
repo_smith/py.typed
repo_smith/repo_smith.py
repo_smith/spec.py
repo_smith/types.py
repo_smith/version.py
repo_smith/helpers/command_spec.py
repo_smith/helpers/files_helper.py
repo_smith/helpers/helper.py
repo_smith/helpers/git_helper/add_options.py
repo_smith/helpers/git_helper/branch_options.py
repo_smith/helpers/git_helper/checkout_options.py
repo_smith/helpers/git_helper/commit_options.py
repo_smith/helpers/git_helper/fetch_options.py
repo_smith/helpers/git_helper/git_helper.py
repo_smith/helpers/git_helper/init_options.py
repo_smith/helpers/git_helper/merge_options.py
repo_smith/helpers/git_helper/push_options.py
repo_smith/helpers/git_helper/remote_options.py
repo_smith/helpers/git_helper/reset_options.py
repo_smith/helpers/git_helper/restore_options.py
repo_smith/helpers/git_helper/revert_options.py
repo_smith/helpers/git_helper/tag_options.py
repo_smith/helpers/github_cli_helper/api_options.py
repo_smith/helpers/github_cli_helper/fields.py
repo_smith/helpers/github_cli_helper/github_cli_helper.py
repo_smith/helpers/github_cli_helper/repo_clone_options.py
repo_smith/helpers/github_cli_helper/repo_create_options.py
repo_smith/helpers/github_cli_helper/repo_fork_options.py
repo_smith/helpers/github_cli_helper/repo_view_options.py
repo_smith/steps/add_step.py
repo_smith/steps/bash_step.py
repo_smith/steps/branch_delete_step.py
repo_smith/steps/branch_rename_step.py
repo_smith/steps/branch_step.py
repo_smith/steps/checkout_step.py
repo_smith/steps/commit_step.py
repo_smith/steps/dispatcher.py
repo_smith/steps/fetch_step.py
repo_smith/steps/file_step.py
repo_smith/steps/merge_step.py
repo_smith/steps/remote_step.py
repo_smith/steps/reset_step.py
repo_smith/steps/revert_step.py
repo_smith/steps/step.py
repo_smith/steps/step_type.py
repo_smith/steps/tag_step.py
repo_smith-2.6.1.dist-info/METADATA
repo_smith-2.6.1.dist-info/WHEEL
repo_smith-2.6.1.dist-info/licenses/LICENSE
repo_smith-2.6.1.dist-info/RECORD
