Metadata-Version: 2.4
Name: repo-smith
Version: 2.6.1
Summary: YAML-based configuration for initializing Git repositories for unit testing
Project-URL: Homepage, https://github.com/git-mastery/repo-smith.git
Project-URL: Repository, https://github.com/git-mastery/repo-smith.git
Project-URL: Issues, https://github.com/git-mastery/repo-smith/issues
Author-email: "Jiahao, Woo" <woojiahao1234@gmail.com>
License: MIT License
License-File: LICENSE
Classifier: Development Status :: 4 - Beta
Classifier: Intended Audience :: Developers
Classifier: Programming Language :: Python :: 3.13
Classifier: Topic :: Software Development
Requires-Python: >=3.13
Requires-Dist: gitpython
Requires-Dist: pyyaml
Requires-Dist: types-pyyaml
